lap/__init__.py
lap/_lapjv.cp311-win_amd64.pyd
lap/lapmod.py
lap/tests/__init__.py
lap/tests/cost_eps.csv.gz
lap/tests/test_arr_loop.py
lap/tests/test_lapjv.py
lap/tests/test_lapmod.py
lap/tests/test_utils.py
lap_sdist-0.5.dev0.dist-info/LICENSE
lap_sdist-0.5.dev0.dist-info/METADATA
lap_sdist-0.5.dev0.dist-info/WHEEL
lap_sdist-0.5.dev0.dist-info/top_level.txt
lap_sdist-0.5.dev0.dist-info/RECORD
