Metadata-Version: 2.1
Name: lap-sdist
Version: 0.5.dev0
Summary: Linear Assignment Problem solver (LAPJV/LAPMOD).
Home-page: https://github.com/gatagat/lap
Download-URL: https://github.com/gatagat/lap
Maintainer: Tomas Kazmar
Maintainer-email: tomash.kazmar@seznam.cz
License: BSD (2-clause)
Classifier: Development Status :: 4 - Beta
Classifier: Environment :: Console
Classifier: Intended Audience :: Science/Research
Classifier: Intended Audience :: Developers
Classifier: Programming Language :: C
Classifier: Programming Language :: Python
Classifier: Programming Language :: Python :: 2
Classifier: Programming Language :: Python :: 3
Classifier: Programming Language :: Python :: 2.7
Classifier: Programming Language :: Python :: 3.7
Classifier: Programming Language :: Python :: 3.8
Classifier: Programming Language :: Python :: 3.9
Classifier: Operating System :: Microsoft :: Windows
Classifier: Operating System :: POSIX
Classifier: Operating System :: Unix
Classifier: Operating System :: MacOS
License-File: LICENSE
Provides-Extra: alldeps
Requires-Dist: numpy (>=1.10.1) ; extra == 'alldeps'
